{
    "_id": "italicus-rosolio-di-bergamotto",
    "_parent_id": null,
    "name": "Italicus Rosolio di Bergamotto",
    "strength": 20,
    "description": "Italicus Rosolio di Bergamotto is an Italian liqueur based around the brilliance of bergamot! By combining Italian bergamot alongside a selection of other tasty botanicals including chamomile, lavender, Melissa balm and more, the producers have made a tipple excellent for enjoying on toasty evenings in the summer. Enjoy over ice, or splashed in a glass of Prosecco.",
    "origin": "Italy",
    "color": "#ffffff",
    "category": "Liqueurs",
    "created_at": "2024-08-24T14:39:10+00:00",
    "updated_at": null,
    "images": [
        {
            "uri": "file:///italicus-rosolio-di-bergamotto-1_EvT0yN.png",
            "sort": 1,
            "placeholder_hash": "pqiFJQwPWB+nRYh3hyhwdwV3BweGhnVlWA",
            "copyright": "Italicus"
        }
    ],
    "ingredient_parts": [],
    "prices": []
}